plone.app.textfield-3.0.1-py3.13-nspkg.pth
plone/app/textfield/TODO.rst
plone/app/textfield/__init__.py
plone/app/textfield/browser.py
plone/app/textfield/browser.zcml
plone/app/textfield/configure.zcml
plone/app/textfield/editor.py
plone/app/textfield/editor.zcml
plone/app/textfield/field.rst
plone/app/textfield/handler.py
plone/app/textfield/handler.rst
plone/app/textfield/handler.zcml
plone/app/textfield/interfaces.py
plone/app/textfield/marshaler.py
plone/app/textfield/marshaler.rst
plone/app/textfield/marshaler.zcml
plone/app/textfield/richtext_widget.rst
plone/app/textfield/tests.py
plone/app/textfield/transform.py
plone/app/textfield/transform.zcml
plone/app/textfield/utils.py
plone/app/textfield/value.py
plone/app/textfield/widget.py
plone/app/textfield/widget.zcml
plone/app/textfield/widget_display.pt
plone/app/textfield/widget_input.pt
plone/app/textfield/widget_textarea_display.pt
plone_app_textfield-3.0.1.dist-info/METADATA
plone_app_textfield-3.0.1.dist-info/WHEEL
plone_app_textfield-3.0.1.dist-info/namespace_packages.txt
plone_app_textfield-3.0.1.dist-info/top_level.txt
plone_app_textfield-3.0.1.dist-info/RECORD
