Metadata-Version: 2.4
Name: plone.app.textfield
Version: 3.0.1
Summary: Text field with MIME type support
Home-page: https://pypi.org/project/plone.app.textfield
Author: Martin Aspeli
Author-email: optilude@gmail.com
License: GPL
Keywords: plone schema field
Classifier: Development Status :: 5 - Production/Stable
Classifier: Framework :: Plone
Classifier: Framework :: Plone :: 6.0
Classifier: Framework :: Plone :: Core
Classifier: License :: OSI Approved :: GNU General Public License (GPL)
Classifier: Programming Language :: Python
Classifier: Programming Language :: Python :: 3.8
Classifier: Programming Language :: Python :: 3.9
Classifier: Programming Language :: Python :: 3.10
Classifier: Programming Language :: Python :: 3.11
Classifier: Topic :: Software Development :: Libraries :: Python Modules
Requires-Python: >=3.8
Requires-Dist: setuptools
Requires-Dist: plone.base
Requires-Dist: Zope
Provides-Extra: portaltransforms
Requires-Dist: Products.PortalTransforms; extra == "portaltransforms"
Provides-Extra: supermodel
Requires-Dist: plone.supermodel; extra == "supermodel"
Provides-Extra: widget
Requires-Dist: z3c.form; extra == "widget"
Provides-Extra: marshaler
Requires-Dist: plone.rfc822; extra == "marshaler"
Provides-Extra: editor
Requires-Dist: plone.schemaeditor; extra == "editor"
Provides-Extra: tests
Requires-Dist: lxml; extra == "tests"
Requires-Dist: plone.app.testing; extra == "tests"
Requires-Dist: plone.supermodel[test]; extra == "tests"
Requires-Dist: plone.testing; extra == "tests"
Dynamic: author
Dynamic: author-email
Dynamic: classifier
Dynamic: description
Dynamic: description-content-type
Dynamic: home-page
Dynamic: keywords
Dynamic: license
Dynamic: provides-extra
Dynamic: requires-dist
Dynamic: requires-python
Dynamic: summary
